orjson/__init__.py
orjson/__init__.pyi
orjson/orjson.cpython-312.so
orjson/py.typed
orjson_qpython-3.10.11.dist-info/METADATA
orjson_qpython-3.10.11.dist-info/WHEEL
orjson_qpython-3.10.11.dist-info/top_level.txt
orjson_qpython-3.10.11.dist-info/RECORD
